LICENSE
README.md
setup.cfg
setup.py
nxtoascii/__init__.py
nxtoascii/__main__.py
nxtoascii/converter.py
nxtoascii.egg-info/PKG-INFO
nxtoascii.egg-info/SOURCES.txt
nxtoascii.egg-info/dependency_links.txt
nxtoascii.egg-info/entry_points.txt
nxtoascii.egg-info/requires.txt
nxtoascii.egg-info/top_level.txt
nxtoascii/tests/__init__.py
nxtoascii/tests/conftest.py
nxtoascii/tests/test_converter.py