Metadata-Version: 2.1
Name: nxtoascii
Version: 0.0.1a1
Summary: Convert a BLISS HDF5 file to SPEC, MULTISPEC, CSV or a generic ASCII columns file
Home-page: https://gitlab.esrf.fr/denolf/nxtoascii
Author: ESRF
Author-email: wout.de_nolf@esrf.fr
License: MIT
Project-URL: Source, https://gitlab.esrf.fr/denolf/nxtoascii
Project-URL: Tracker, https://gitlab.esrf.fr/denolf/nxtoascii/issues
Platform: UNKNOWN
Classifier: Intended Audience :: Science/Research
Classifier: License :: OSI Approved :: MIT License
Classifier: Programming Language :: Python :: 3
Provides-Extra: test
Provides-Extra: dev
License-File: LICENSE
